omuplugin_discordrpc/__init__.py
omuplugin_discordrpc/const.py
omuplugin_discordrpc/permissions.py
omuplugin_discordrpc/plugin.py
omuplugin_discordrpc/types.py
omuplugin_discordrpc/version.py
omuplugin_discordrpc/discordrpc/__init__.py
omuplugin_discordrpc/discordrpc/client.py
omuplugin_discordrpc/discordrpc/payloads.py
omuplugin_discordrpc-0.9.24.dist-info/METADATA
omuplugin_discordrpc-0.9.24.dist-info/WHEEL
omuplugin_discordrpc-0.9.24.dist-info/entry_points.txt
omuplugin_discordrpc-0.9.24.dist-info/RECORD
